UVEC/__init__.py
UVEC/__version__.py
UVEC/get_path_uvec.py
UVEC/uvec_ten_dof_vehicle_2D/__init__.py
UVEC/uvec_ten_dof_vehicle_2D/base_model.py
UVEC/uvec_ten_dof_vehicle_2D/hertzian_contact.py
UVEC/uvec_ten_dof_vehicle_2D/irregularities.py
UVEC/uvec_ten_dof_vehicle_2D/newmark_solver.py
UVEC/uvec_ten_dof_vehicle_2D/uvec.py
UVEC/uvec_two_dof_vehicle_2D/__init__.py
UVEC/uvec_two_dof_vehicle_2D/uvec.py
uvec-1.1.2.dist-info/licenses/LICENSE
uvec-1.1.2.dist-info/METADATA
uvec-1.1.2.dist-info/WHEEL
uvec-1.1.2.dist-info/top_level.txt
uvec-1.1.2.dist-info/RECORD
