Metadata-Version: 2.4
Name: UVEC
Version: 1.1.2
Summary: User defined VEhiCle models [UVEC]
Author: attr: UVEC.__author__
Classifier: Programming Language :: Python :: 3
Classifier: License :: OSI Approved :: BSD License
Classifier: Operating System :: Microsoft :: Windows
Classifier: Operating System :: Unix
Requires-Python: >=3.9
License-File: LICENSE
Requires-Dist: numpy>=2.0.2
Requires-Dist: matplotlib>=3.9.3
Provides-Extra: testing
Requires-Dist: pytest>=8.3; extra == "testing"
Requires-Dist: pytest-cov>=6.0; extra == "testing"
Requires-Dist: tox>=4.23; extra == "testing"
Requires-Dist: mypy>=1.13; extra == "testing"
Requires-Dist: yapf>=0.43; extra == "testing"
Dynamic: license-file
